Trio_UnifiedApi.cp312-win32.pyd
Trio_UnifiedApi_PCMCAT.dll
Trio_UnifiedApi_TCP.dll
trio_unifiedapi-1.2.0.dist-info/METADATA
trio_unifiedapi-1.2.0.dist-info/WHEEL
trio_unifiedapi-1.2.0.dist-info/licenses/LICENSE.md
trio_unifiedapi-1.2.0.dist-info/RECORD
