Metadata-Version: 2.2
Name: Trio_UnifiedApi
Version: 1.2.0
Summary: Python binding of Trio Unified API
Author: Trio Motion Technology
Maintainer-Email: Boris Dachev <bdachev@triomotion.com>
Classifier: Development Status :: 5 - Production/Stable
Classifier: Programming Language :: Python :: 3
Classifier: Programming Language :: Python :: 3.8
Classifier: Programming Language :: Python :: 3.11
Classifier: Programming Language :: Python :: 3.12
Classifier: Programming Language :: Python :: 3.13
Classifier: Programming Language :: C++
Classifier: Intended Audience :: Developers
Classifier: License :: Other/Proprietary License
Classifier: Operating System :: Microsoft :: Windows :: Windows 10
Classifier: Operating System :: Microsoft :: Windows :: Windows 11
Classifier: Operating System :: POSIX :: Linux
Classifier: Natural Language :: English
Project-URL: Homepage, https://github.com/Trio-Motion-Technology/UnifiedAPI
Requires-Python: >=3.7
Requires-Dist: numpy
